Workbook

Sheet Summary
A1: Doondo V2 — Cost to Complete & Launch Nationally + 12-Month Runway
A2: Scenario: founder completes remaining development in-house · India-wide public launch · budget covers launch + 12 months of operations · all figures in INR (₹)
A4: Cost Category | B4: Low (₹) | C4: Expected (₹) | D4: High (₹)
A5: One-time & Year-1 fixed costs | B5: ='One-Time & Year 1'!B16 -> 119100 | C5: ='One-Time & Year 1'!C16 -> 286600 | D5: ='One-Time & Year 1'!D16 -> 640600
A6: Recurring infrastructure & services (12 months) | B6: ='Recurring Costs'!E9+'Recurring Costs'!E18 -> 397200 | C6: ='Recurring Costs'!F9+'Recurring Costs'!F18 -> 963600 | D6: ='Recurring Costs'!G9+'Recurring Costs'!G18 -> 2439600
A7: Operations & support (12 months) | B7: ='Recurring Costs'!E23 -> 0 | C7: ='Recurring Costs'!F23 -> 420000 | D7: ='Recurring Costs'!G23 -> 1380000
A8: Marketing & user acquisition (12 months) | B8: ='Marketing & Growth'!B8 -> 250000 | C8: ='Marketing & Growth'!C8 -> 937000 | D8: ='Marketing & Growth'!D8 -> 4130000
A9: Subtotal | B9: =SUM(B5:B8) -> 766300 | C9: =SUM(C5:C8) -> 2607200 | D9: =SUM(D5:D8) -> 8590200
A10: Contingency buffer | B10: =B9*$B$14 -> 91956 | C10: =C9*$B$14 -> 312864 | D10: =D9*$B$14 -> 1030824
A11: GRAND TOTAL — cost to launch + 12 months | B11: =B9+B10 -> 858256 | C11: =C9+C10 -> 2920064 | D11: =D9+D10 -> 9621024
A14: Contingency rate (editable assumption) | B14: 0.12
A16: How to read this budget
A17: • Low = bare-bones bootstrap (founder also does support; lean marketing). Expected = a realistic lean national launch. High = aggressive paid-acquisition push.
A18: • The single biggest swing is marketing. Infrastructure and AI-API costs scale with how many users actually join — they start low and ramp.
A19: • Developer salaries are excluded — you are completing the build yourself. See the 'Assumptions & Notes' tab for everything included and excluded.
A20: • Partner-funded items (insurance underwriting, worker-advance lending capital, payment escrow float) are NOT in this budget — see notes tab.

Sheet One-Time & Year 1
A1: One-Time / Setup & Year-1 Fixed Costs (₹)
A2: Item | B2: Low | C2: Expected | D2: High | E2: Notes
A3: Private Limited Company incorporation | B3: 8000 | C3: 15000 | D3: 25000 | E3: MCA registration, DSC, DIN, PAN/TAN. Needed to handle payments, data & partnerships.
A4: Trademark registration — 'Doondo' brand (2 classes) | B4: 9000 | C4: 18000 | D4: 30000 | E4: Govt fee ₹4,500/class (startup rate) + attorney fee. Classes 9 (app) & 35/42 (services).
A5: Legal — Terms of Service, Privacy Policy, user/employer agreements | B5: 20000 | C5: 40000 | D5: 75000 | E5: Essential: app handles UPI payments, worker PII, women-safety data, insurance & advances.
A6: Apple Developer Program (first year) | B6: 8500 | C6: 8500 | D6: 8500 | E6: USD 99/yr. Renews annually.
A7: Google Play Developer registration | B7: 2100 | C7: 2100 | D7: 2100 | E7: USD 25, one-time.
A8: Domain registration (.com / .in) | B8: 1500 | C8: 5000 | D8: 50000 | E8: Standard ~₹1,500/yr; a premium/aftermarket domain can cost far more.
A9: Logo & brand-asset polish | B9: 0 | C9: 8000 | D9: 30000 | E9: Low = do it yourself; higher = freelance designer for full brand kit.
A10: Pre-launch security audit / penetration test | B10: 40000 | C10: 90000 | D10: 175000 | E10: Strongly advised before a payments + PII + women-safety app goes public.
A11: App-store listing creative (screenshots, preview video) | B11: 0 | C11: 10000 | D11: 35000 | E11: Store screenshots in multiple languages + a short preview video.
A12: Test-device pool (Android range + iOS) | B12: 10000 | C12: 20000 | D12: 40000 | E12: Low-end Androids are the core audience — must be tested on real budget hardware.
A13: CA / accounting setup + GST & ROC filings (year 1) | B13: 12000 | C13: 25000 | D13: 50000 | E13: Bookkeeping, GST registration & returns, TDS.
A14: Statutory annual compliance (ROC annual return, audit) | B14: 8000 | C14: 20000 | D14: 45000 | E14: Year-1 company-law compliance and a basic statutory audit.
A15: Business insurance (cyber liability / D&O) | B15: 0 | C15: 25000 | D15: 75000 | E15: Optional year 1; cyber-liability cover is sensible given the data handled.
A16: TOTAL — One-Time & Year-1 Fixed Costs | B16: =SUM(B3:B15) -> 119100 | C16: =SUM(C3:C15) -> 286600 | D16: =SUM(D3:D15) -> 640600

Sheet Recurring Costs
A1: Recurring Costs — Monthly Rate × 12-Month Annual (₹)
A2: Item | B2: Low /mo | C2: Expected /mo | D2: High /mo | E2: Low /yr | F2: Expected /yr | G2: High /yr | H2: Notes
A3: Infrastructure & Hosting
A4: MongoDB Atlas — dedicated cluster | B4: 5000 | C4: 10000 | D4: 22000 | E4: =B4*12 -> 60000 | F4: =C4*12 -> 120000 | G4: =D4*12 -> 264000 | H4: Managed database. Starts small, scales with users; M10–M30 class.
A5: Backend app hosting (servers + load balancer) | B5: 6000 | C5: 12000 | D5: 28000 | E5: =B5*12 -> 72000 | F5: =C5*12 -> 144000 | G5: =D5*12 -> 336000 | H5: Node/Express API. Render/Railway/AWS; 1–3 instances as traffic grows.
A6: Object storage + CDN (photos, voice notes, video reels) | B6: 4000 | C6: 9000 | D6: 25000 | E6: =B6*12 -> 48000 | F6: =C6*12 -> 108000 | G6: =D6*12 -> 300000 | H6: 30-sec Hire Reels are the cost driver — video storage + bandwidth.
A7: Transactional email service | B7: 500 | C7: 1000 | D7: 2500 | E7: =B7*12 -> 6000 | F7: =C7*12 -> 12000 | G7: =D7*12 -> 30000 | H7: OTP backup, receipts, notifications (SES/SendGrid).
A8: Push notifications | B8: 0 | C8: 0 | D8: 2000 | E8: =B8*12 -> 0 | F8: =C8*12 -> 0 | G8: =D8*12 -> 24000 | H8: Expo Push / FCM are free; cost only if a paid tier is used.
A9: Subtotal — Infrastructure & Hosting | B9: =SUM(B4:B8) -> 15500 | C9: =SUM(C4:C8) -> 32000 | D9: =SUM(D4:D8) -> 79500 | E9: =SUM(E4:E8) -> 186000 | F9: =SUM(F4:F8) -> 384000 | G9: =SUM(G4:G8) -> 954000
A10: Third-Party APIs & Tools
A11: AI / LLM API — Anthropic (photo profile, translation, resume, voice agent) | B11: 8000 | C11: 22000 | D11: 60000 | E11: =B11*12 -> 96000 | F11: =C11*12 -> 264000 | G11: =D11*12 -> 720000 | H11: Usage-based. In-chat auto-translate of every message is the main driver; scales with messaging volume.
A12: Speech-to-text / transcription (Indian languages) | B12: 3000 | C12: 8000 | D12: 20000 | E12: =B12*12 -> 36000 | F12: =C12*12 -> 96000 | G12: =D12*12 -> 240000 | H12: Voice-note auto-transcription & voice agent. Sarvam AI / Google STT.
A13: SMS / OTP gateway | B13: 3000 | C13: 7000 | D13: 18000 | E13: =B13*12 -> 36000 | F13: =C13*12 -> 84000 | G13: =D13*12 -> 216000 | H13: Phone verification at national scale. ~₹0.12–0.20 per SMS.
A14: Maps / geolocation API | B14: 2000 | C14: 5000 | D14: 12000 | E14: =B14*12 -> 24000 | F14: =C14*12 -> 60000 | G14: =D14*12 -> 144000 | H14: Jobs map, nearby search, geocoding (Google Maps / Mapbox).
A15: Error monitoring (Sentry) | B15: 0 | C15: 1800 | D15: 2500 | E15: =B15*12 -> 0 | F15: =C15*12 -> 21600 | G15: =D15*12 -> 30000 | H15: Already integrated. Free tier early; paid team plan later.
A16: Product analytics | B16: 0 | C16: 1000 | D16: 3000 | E16: =B16*12 -> 0 | F16: =C16*12 -> 12000 | G16: =D16*12 -> 36000 | H16: Amplitude / PostHog — generous free tiers.
A17: EAS Build (Expo native build service) | B17: 1600 | C17: 3500 | D17: 8300 | E17: =B17*12 -> 19200 | F17: =C17*12 -> 42000 | G17: =D17*12 -> 99600 | H17: Builds the iOS/Android binaries and ships OTA updates.
A18: Subtotal — Third-Party APIs & Tools | B18: =SUM(B11:B17) -> 17600 | C18: =SUM(C11:C17) -> 48300 | D18: =SUM(D11:D17) -> 123800 | E18: =SUM(E11:E17) -> 211200 | F18: =SUM(F11:F17) -> 579600 | G18: =SUM(G11:G17) -> 1485600
A19: Operations & Support
A20: Customer support — regional-language agent(s) | B20: 0 | C20: 22000 | D20: 70000 | E20: =B20*12 -> 0 | F20: =C20*12 -> 264000 | G20: =D20*12 -> 840000 | H20: Low = founder handles it solo; Expected = 1 agent; High = 3-person desk for national coverage.
A21: Content moderation / trust & safety (reels, reviews, SOS) | B21: 0 | C21: 8000 | D21: 30000 | E21: =B21*12 -> 0 | F21: =C21*12 -> 96000 | G21: =D21*12 -> 360000 | H21: Video reels and reviews need moderation; part-time at first.
A22: Ops for manual advance & insurance processing | B22: 0 | C22: 5000 | D22: 15000 | E22: =B22*12 -> 0 | F22: =C22*12 -> 60000 | G22: =D22*12 -> 180000 | H22: V1 advances & insurance are ops-processed manually until partners are wired.
A23: Subtotal — Operations & Support (Annual) | B23: =SUM(B20:B22) -> 0 | C23: =SUM(C20:C22) -> 35000 | D23: =SUM(D20:D22) -> 115000 | E23: =SUM(E20:E22) -> 0 | F23: =SUM(F20:F22) -> 420000 | G23: =SUM(G20:G22) -> 1380000
A25: TOTAL RECURRING (Annual, 12 months) | E25: =E9+E18+E23 -> 397200 | F25: =F9+F18+F23 -> 1383600 | G25: =G9+G18+G23 -> 3819600

Sheet Marketing & Growth
A1: Marketing & User Acquisition — 12-Month Budget (₹)
A2: Item | B2: Low | C2: Expected | D2: High | E2: Notes
A3: Digital advertising / user acquisition (Google, Meta) | B3: 150000 | C3: 500000 | D3: 2500000 | E3: The dominant, most scalable line. National paid acquisition; spend as far as the budget allows.
A4: On-ground / field marketing | B4: 50000 | C4: 200000 | D4: 800000 | E4: Worker hubs, labour-market partnerships, posters — key for reaching blue-collar users.
A5: Referral incentive pool (₹100 × 2, refer-a-friend) | B5: 50000 | C5: 150000 | D5: 500000 | E5: Real cash paid to users. Both referrer and referee get ₹100 on the first shift.
A6: Content, social & influencer | B6: 0 | C6: 75000 | D6: 300000 | E6: Regional-language video content and micro-influencers in target trades.
A7: ASO tools & subscriptions | B7: 0 | C7: 12000 | D7: 30000 | E7: App-store optimisation tooling and keyword tracking.
A8: TOTAL — Marketing & Growth (12 months) | B8: =SUM(B3:B7) -> 250000 | C8: =SUM(C3:C7) -> 937000 | D8: =SUM(D3:D7) -> 4130000

Sheet Assumptions & Notes
A1: Assumptions, Inclusions & Exclusions
A3: Scenario this budget models
A4: • You complete the remaining development yourself — no developer salaries are included.
A5: • Public launch is India-wide (national). Infrastructure, support and marketing are sized for that reach.
A6: • The budget covers everything up to launch PLUS the first 12 months of operations.
A7: • All figures are in Indian Rupees (₹). USD-priced services converted at ~₹84/USD.
A8: • Project state at audit: 31 of 46 features shipped, 6 partial, 9 not started, plus translation QA and a real-DB boot test.
A10: What IS included
A11: • Company setup, trademark, legal documents and year-1 statutory compliance.
A12: • Apple & Google developer accounts and a pre-launch security audit.
A13: • 12 months of hosting, database, storage/CDN, and all third-party APIs (AI, transcription, SMS, maps).
A14: • 12 months of customer support, content moderation, and manual ops for advances/insurance.
... A41: Prepared from a code + roadmap audit of the Doondo V2 repository, 25 May 2026.
